{
  "title": "Как мы работаем",
  "description": "Компания предоставляет аренду компьютеров с техподдержкой. Игровые и бизнес-конфигурации, онлайн-заказ, доставка",
  "content": "Мы заботимся о вашем комфорте, обеспечивая доставку, подключение и техническую поддержку на всем протяжении договора. С целью вашей безопасности, заключается прозрачный договор аренды, а также вы получаете скидки и бонусы при оформлении заказа. Наша компетентная команда также поможет с размещением и подключением оборудования, чтобы ваш опыт работы с нами был максимально приятным и беспроблемным. Мы ценим ваше доверие и стремимся к долгосрочному и успешному сотрудничеству",
  "promotions": [
    {
      "title": "2 дня",
      "commentary": "FREE",
      "description": "При аренде на 1 неделю"
    },
    {
      "title": "8 дней",
      "commentary": "Бесплатно",
      "description": "При аренде на 1 месяц"
    },
    {
      "title": "1 мес",
      "commentary": "за 0 руб",
      "description": "При аренде на 4 месяца"
    }
  ]
}